uuttaminen/__init__.py
uuttaminen/__main__.py
uuttaminen/api.py
uuttaminen/cli.py
uuttaminen/implementation.py
uuttaminen-2023.1.28.dist-info/LICENSE
uuttaminen-2023.1.28.dist-info/METADATA
uuttaminen-2023.1.28.dist-info/WHEEL
uuttaminen-2023.1.28.dist-info/entry_points.txt
uuttaminen-2023.1.28.dist-info/top_level.txt
uuttaminen-2023.1.28.dist-info/RECORD
