Metadata-Version: 2.1
Name: uuttaminen
Version: 2023.1.28
Summary: Extraction (Finnish: uuttaminen) of source code for embedding into markdown documents as fenced blocks.
Author-email: Stefan Hagen <stefan@hagen.link>
Maintainer-email: Stefan Hagen <stefan@hagen.link>
Project-URL: Homepage, https://git.sr.ht/~sthagen/uuttaminen
Project-URL: Bug-Tracker, https://todo.sr.ht/~sthagen/uuttaminen
Project-URL: Documentation, https://codes.dilettant.life/docs/uuttaminen
Project-URL: Source-Code, https://git.sr.ht/~sthagen/uuttaminen
Project-URL: Test-Coverage, https://codes.dilettant.life/coverage/uuttaminen
Keywords: developer-tools,devops
Classifier: Development Status :: 3 - Alpha
Classifier: Intended Audience :: Developers
Classifier: License :: OSI Approved :: MIT License
Classifier: Programming Language :: Python :: 3.10
Classifier: Programming Language :: Python :: 3.11
Classifier: Programming Language :: Python :: 3.9
Requires-Python: >=3.9
License-File: LICENSE
Requires-Dist: GitPython (>=3.1.30)
Requires-Dist: PyYAML (>=6.0)
Requires-Dist: typer (>=0.7.0)
Provides-Extra: dev
Requires-Dist: black ; extra == 'dev'
Requires-Dist: coverage ; extra == 'dev'
Requires-Dist: hypothesis ; extra == 'dev'
Requires-Dist: mypy ; extra == 'dev'
Requires-Dist: pytest ; extra == 'dev'
Requires-Dist: pytest-cov ; extra == 'dev'
Requires-Dist: pytest-flake8 ; extra == 'dev'
Requires-Dist: ruff ; extra == 'dev'
